ows/__init__.py
ows/decoder.py
ows/exceptions.py
ows/kvp.py
ows/registry.py
ows/test.py
ows/test_util.py
ows/util.py
ows/xml.py
ows/cis/__init__.py
ows/cis/v11.py
ows/common/__init__.py
ows/common/decoders.py
ows/common/test_decoders.py
ows/common/types.py
ows/common/v20/__init__.py
ows/common/v20/decoders.py
ows/common/v20/encoders.py
ows/common/v20/namespaces.py
ows/common/v20/test_encoders.py
ows/gml/__init__.py
ows/gml/types.py
ows/gml/v32.py
ows/swe/__init__.py
ows/swe/types.py
ows/swe/v20.py
ows/wcs/__init__.py
ows/wcs/types.py
ows/wcs/v20/__init__.py
ows/wcs/v20/decoders.py
ows/wcs/v20/encoders.py
ows/wcs/v20/exceptions.py
ows/wcs/v20/namespaces.py
ows/wcs/v20/test_decoders.py
ows/wcs/v20/test_encoders.py
ows/wcs/v20/types.py
ows/wcs/v20/eo/__init__.py
ows/wcs/v20/eo/decoders.py
ows/wcs/v20/eo/encoders.py
ows/wcs/v20/eo/objects.py
ows/wcs/v21/__init__.py
ows/wcs/v21/encoders.py
ows/wcs/v21/namespaces.py
ows/wcs/v21/test_encoders.py
ows/wms/__init__.py
ows/wms/types.py
ows/wms/v10/__init__.py
ows/wms/v11/__init__.py
ows/wms/v11/encoders.py
ows/wms/v11/namespaces.py
ows/wms/v11/test_encoders.py
ows/wms/v13/__init__.py
ows/wms/v13/decoders.py
ows/wms/v13/encoders.py
ows/wms/v13/namespaces.py
ows/wms/v13/test_decoders.py
ows/wms/v13/test_encoders.py
ows/wps/__init__.py
ows/wps/types.py
ows/wps/v20/__init__.py
ows/wps/v20/decoders.py
ows/wps/v20/encoders.py
ows/wps/v20/namespaces.py
ows/wps/v20/test_decoders.py
ows/wps/v20/test_encoders.py
ows/wps/v20/types.py
pyows-0.3.1.dist-info/METADATA
pyows-0.3.1.dist-info/WHEEL
pyows-0.3.1.dist-info/top_level.txt
pyows-0.3.1.dist-info/RECORD
