Metadata-Version: 2.1
Name: pyows
Version: 0.3.1
Summary: OWS utilities
Home-page: https://github.com/eoxserver/pyows
Author: Fabian Schindler
Author-email: fabian.schindler@eox.at
License: MIT
Classifier: Development Status :: 3 - Alpha
Classifier: Intended Audience :: Developers
Classifier: Topic :: Scientific/Engineering :: GIS
Classifier: License :: OSI Approved :: MIT License
Classifier: Programming Language :: Python :: 3.6
Classifier: Programming Language :: Python :: 3.7
Requires-Dist: iso8601
Requires-Dist: lxml
Requires-Dist: dataclasses ; python_version < "3.7"
